{"docs":{"name":"Keyforge Compendium API","info":"\n\u003cp\u003eThe Keyforge Compendium API uses \u0026#39;Basic Access Authentication\u0026#39;\nwhere the key is the username and the secret is the password. Most\nlibraries come with build in support for this if not you will have to built\nthe header yourself.\u003c/p\u003e\n","copyright":"© 2018-2019 - keyforge-compendium.com","doc_url":"../../docs/1.0","api_url":"/api/v1","resources":[{"doc_url":"../../docs/1.0/cards","id":"cards","api_url":"/api/v1","name":"Cards","short_description":"The cards API lets you lookup all individual cards.","full_description":"","version":"1.0","formats":null,"metadata":null,"methods":[{"doc_url":"../../docs/1.0/cards/show","name":"show","apis":[{"api_url":"/api/v1/cards/:id.json","http_method":"GET","short_description":"Show card details","deprecated":null},{"api_url":"/api/v1/sets/:set_id/cards/:id.json","http_method":"GET","short_description":"Show card details for given set","deprecated":null}],"formats":null,"full_description":"","errors":[],"params":[{"name":"id","full_name":"id","description":"\n\u003cp\u003eCard number\u003c/p\u003e\n","required":false,"allow_nil":false,"allow_blank":false,"validator":"Must be a Integer","expected_type":"numeric","metadata":null,"show":true,"validations":[]},{"name":"set_id","full_name":"set_id","description":"\n\u003cp\u003eSet id. 1 for “Call of the Archons”, 2 for “Age of Ascension”\u003c/p\u003e\n","required":false,"allow_nil":false,"allow_blank":false,"validator":"Must be one of: \u003ccode\u003e1\u003c/code\u003e, \u003ccode\u003e2\u003c/code\u003e.","expected_type":"string","metadata":null,"show":true,"validations":[]}],"returns":[{"code":200,"description":"OK","is_array":false,"returns_object":[{"name":"title","full_name":"title","description":"\n\u003cp\u003eTitle of the card\u003c/p\u003e\n","required":true,"allow_nil":false,"allow_blank":false,"validator":"Must be a String","expected_type":"string","metadata":null,"show":true},{"name":"number","full_name":"number","description":"\n\u003cp\u003eOfficial card number\u003c/p\u003e\n","required":true,"allow_nil":false,"allow_blank":false,"validator":"Must be a Integer","expected_type":"numeric","metadata":null,"show":true},{"name":"card_type","full_name":"card_type","description":"\n\u003cp\u003eCard type\u003c/p\u003e\n","required":true,"allow_nil":false,"allow_blank":false,"validator":"Must be a String","expected_type":"string","metadata":null,"show":true},{"name":"front_image","full_name":"front_image","description":"\n\u003cp\u003eURL to card image\u003c/p\u003e\n","required":true,"allow_nil":false,"allow_blank":false,"validator":"Must be a String","expected_type":"string","metadata":null,"show":true},{"name":"text","full_name":"text","description":"\n\u003cp\u003eCard text\u003c/p\u003e\n","required":true,"allow_nil":false,"allow_blank":false,"validator":"Must be a String","expected_type":"string","metadata":null,"show":true},{"name":"traits","full_name":"traits","description":"\n\u003cp\u003eCard traits\u003c/p\u003e\n","required":true,"allow_nil":false,"allow_blank":false,"validator":"Must be a String","expected_type":"string","metadata":null,"show":true},{"name":"rarity","full_name":"rarity","description":"\n\u003cp\u003eCard rarity\u003c/p\u003e\n","required":true,"allow_nil":false,"allow_blank":false,"validator":"Must be a String","expected_type":"string","metadata":null,"show":true},{"name":"artist","full_name":"artist","description":"\n\u003cp\u003eCard artist\u003c/p\u003e\n","required":true,"allow_nil":false,"allow_blank":false,"validator":"Must be a String","expected_type":"string","metadata":null,"show":true},{"name":"house_name","full_name":"house_name","description":"\n\u003cp\u003eCard house name\u003c/p\u003e\n","required":true,"allow_nil":false,"allow_blank":false,"validator":"Must be a String","expected_type":"string","metadata":null,"show":true},{"name":"amber","full_name":"amber","description":"\n\u003cp\u003eCard bonus aember\u003c/p\u003e\n","required":true,"allow_nil":false,"allow_blank":false,"validator":"Must be a Integer","expected_type":"numeric","metadata":null,"show":true},{"name":"power","full_name":"power","description":"\n\u003cp\u003eCard power\u003c/p\u003e\n","required":true,"allow_nil":false,"allow_blank":false,"validator":"Must be a Integer","expected_type":"numeric","metadata":null,"show":true},{"name":"armor","full_name":"armor","description":"\n\u003cp\u003eCard armor\u003c/p\u003e\n","required":true,"allow_nil":false,"allow_blank":false,"validator":"Must be a Integer","expected_type":"numeric","metadata":null,"show":true},{"name":"cards_decks_count","full_name":"cards_decks_count","description":"\n\u003cp\u003eCard is present in # amount of decks\u003c/p\u003e\n","required":true,"allow_nil":false,"allow_blank":false,"validator":"Must be a Integer","expected_type":"numeric","metadata":null,"show":true},{"name":"faqs","full_name":"faqs","description":"\n\u003cp\u003eFAQs for this card\u003c/p\u003e\n","required":true,"allow_nil":false,"allow_blank":false,"validator":"Must be a Hash","expected_type":"hash","metadata":null,"show":true,"params":[{"name":"id","full_name":"faqs[id]","description":"\n\u003cp\u003eFAQ id\u003c/p\u003e\n","required":true,"allow_nil":false,"allow_blank":false,"validator":"Must be a Integer","expected_type":"numeric","metadata":null,"show":true,"validations":[]},{"name":"question","full_name":"faqs[question]","description":"\n\u003cp\u003eFAQ question\u003c/p\u003e\n","required":true,"allow_nil":false,"allow_blank":false,"validator":"Must be a String","expected_type":"string","metadata":null,"show":true,"validations":[]},{"name":"answer","full_name":"faqs[answer]","description":"\n\u003cp\u003eFAQ Answer\u003c/p\u003e\n","required":true,"allow_nil":false,"allow_blank":false,"validator":"Must be a String","expected_type":"string","metadata":null,"show":true,"validations":[]}]}],"additional_properties":false}],"examples":[],"metadata":null,"see":[],"headers":[],"show":true}],"headers":[],"deprecated":false}],"link_extension":".html"}}